{"stats":{"minecraft:custom":{"minecraft:jump":171,"minecraft:open_chest":2,"minecraft:time_since_rest":4234,"minecraft:leave_game":1,"minecraft:play_one_minute":4234,"minecraft:interact_with_furnace":4,"minecraft:damage_taken":100,"minecraft:sprint_one_cm":23062,"minecraft:walk_on_water_one_cm":2838,"minecraft:time_since_death":4234,"minecraft:walk_one_cm":5706,"minecraft:climb_one_cm":1261,"minecraft:walk_under_water_one_cm":127,"minecraft:swim_one_cm":1764,"minecraft:interact_with_crafting_table":1,"minecraft:fall_one_cm":4594,"minecraft:fly_one_cm":41326}},"DataVersion":2230}